{
  "data": {
    "article": {},
    "attachments": {},
    "author_id": "2045598149704818688",
    "conversation_id": "2065324029662388464",
    "created_at": "2026-06-13T01:43:40.000Z",
    "edit_controls": {
      "editable_until": "2026-06-13T02:43:40.000Z",
      "edits_remaining": 5,
      "is_edit_eligible": false
    },
    "edit_history_tweet_ids": [
      "2065611024720601206"
    ],
    "entities": {
      "mentions": [
        {
          "end": 15,
          "id": "2056401506791026689",
          "start": 0,
          "username": "entivv14xiRcrd"
        }
      ]
    },
    "geo": {},
    "id": "2065611024720601206",
    "in_reply_to_user_id": "2056401506791026689",
    "lang": "ja",
    "note_tweet": {
      "entities": {}
    },
    "possibly_sensitive": false,
    "public_metrics": {
      "bookmark_count": 0,
      "impression_count": 0,
      "like_count": 0,
      "quote_count": 0,
      "reply_count": 0,
      "retweet_count": 0
    },
    "referenced_tweets": [
      {
        "id": "2065594129833426996",
        "type": "replied_to"
      }
    ],
    "reply_settings": "everyone",
    "text": "@entivv14xiRcrd 嘿嘿！"
  },
  "includes": {
    "tweets": [
      {
        "article": {},
        "attachments": {},
        "author_id": "2045598149704818688",
        "conversation_id": "2065324029662388464",
        "created_at": "2026-06-13T01:43:40.000Z",
        "edit_controls": {
          "editable_until": "2026-06-13T02:43:40.000Z",
          "edits_remaining": 5,
          "is_edit_eligible": false
        },
        "edit_history_tweet_ids": [
          "2065611024720601206"
        ],
        "entities": {
          "mentions": [
            {
              "end": 15,
              "id": "2056401506791026689",
              "start": 0,
              "username": "entivv14xiRcrd"
            }
          ]
        },
        "geo": {},
        "id": "2065611024720601206",
        "in_reply_to_user_id": "2056401506791026689",
        "lang": "ja",
        "note_tweet": {
          "entities": {}
        },
        "possibly_sensitive": false,
        "public_metrics": {
          "bookmark_count": 0,
          "impression_count": 0,
          "like_count": 0,
          "quote_count": 0,
          "reply_count": 0,
          "retweet_count": 0
        },
        "referenced_tweets": [
          {
            "id": "2065594129833426996",
            "type": "replied_to"
          }
        ],
        "reply_settings": "everyone",
        "text": "@entivv14xiRcrd 嘿嘿！"
      },
      {
        "article": {},
        "attachments": {},
        "author_id": "2056401506791026689",
        "conversation_id": "2065324029662388464",
        "created_at": "2026-06-13T00:36:32.000Z",
        "edit_controls": {
          "editable_until": "2026-06-13T01:36:32.000Z",
          "edits_remaining": 5,
          "is_edit_eligible": false
        },
        "edit_history_tweet_ids": [
          "2065594129833426996"
        ],
        "entities": {
          "mentions": [
            {
              "end": 9,
              "id": "2045598149704818688",
              "start": 0,
              "username": "Dodioibs"
            }
          ]
        },
        "geo": {},
        "id": "2065594129833426996",
        "in_reply_to_user_id": "2045598149704818688",
        "lang": "zh",
        "note_tweet": {
          "entities": {}
        },
        "possibly_sensitive": false,
        "public_metrics": {
          "bookmark_count": 0,
          "impression_count": 4,
          "like_count": 0,
          "quote_count": 0,
          "reply_count": 1,
          "retweet_count": 0
        },
        "referenced_tweets": [
          {
            "id": "2065324029662388464",
            "type": "replied_to"
          }
        ],
        "reply_settings": "everyone",
        "text": "@Dodioibs 多可爱的宝宝"
      }
    ],
    "users": [
      {
        "created_at": "2026-04-18T20:21:35.000Z",
        "description": "中式地雷餐券女 自傷 od bpd｜\n防炸@dooaisuan\n爱人@c10n3_f\n女友@lyxtd3s",
        "entities": {
          "description": {
            "mentions": [
              {
                "end": 31,
                "start": 21,
                "username": "dooaisuan"
              },
              {
                "end": 42,
                "start": 34,
                "username": "c10n3_f"
              },
              {
                "end": 53,
                "start": 45,
                "username": "lyxtd3s"
              }
            ]
          }
        },
        "id": "2045598149704818688",
        "location": "痛苦深淵",
        "name": "小酸2.0（寻回推友中）",
        "pinned_tweet_id": "2065326000926597313",
        "profile_image_url": "https://pbs.twimg.com/profile_images/2053503237328941056/f1Yda8hz_normal.jpg",
        "protected": false,
        "public_metrics": {
          "followers_count": 339,
          "following_count": 245,
          "like_count": 928,
          "listed_count": 0,
          "media_count": 57,
          "tweet_count": 826
        },
        "username": "Dodioibs",
        "verified": false
      },
      {
        "created_at": "2026-05-18T15:49:48.000Z",
        "description": "喜欢喜欢我的人类｜大家都来找我fo口牙",
        "id": "2056401506791026689",
        "name": "闭上眼睛就能看到我的未来",
        "pinned_tweet_id": "2065602814966145294",
        "profile_image_url": "https://pbs.twimg.com/profile_images/2065596171419369472/WRyE-SbZ_normal.jpg",
        "protected": false,
        "public_metrics": {
          "followers_count": 2,
          "following_count": 6,
          "like_count": 17,
          "listed_count": 0,
          "media_count": 2,
          "tweet_count": 39
        },
        "username": "entivv14xiRcrd",
        "verified": false
      }
    ]
  }
}